[{"title":"大量店铺转让，小饼「内卷」带来供应过剩，淄博烧烤「凉」了吗？为什么会出现这种现象？","url":"https://www.zhihu.com/question/610461393"},{"title":"美国总统参选人表示「中国周边有 313 个美军基地，其他国家会觉得谁对全球安全威胁更大」，如何评价？","url":"https://www.zhihu.com/question/610542360"},{"title":"为什么李玟明明看起来那么开朗自信，却罹患抑郁症？","url":"https://www.zhihu.com/question/610557808"},{"title":"房地产业低迷，百万农民工被迫失业或转行，当农民工「退休」，收入下滑焦虑在家庭弥漫，如何保障他们的生活？","url":"https://www.zhihu.com/question/610633138"},{"title":"为什么《英雄联盟》热度就是降不下来？","url":"https://www.zhihu.com/question/582973653"},{"title":"我国首个开源桌面操作系统「开放麒麟 1.0」发布，有哪些技术亮点？对我国国产操作系统有何意义？","url":"https://www.zhihu.com/question/610513030"},{"title":"美联储 6 月会议纪要「几乎所有官员都表示，可能会进一步收紧货币政策」，释放了什么信号？","url":"https://www.zhihu.com/question/610625334"},{"title":"电视剧《长安十二时辰》里的「第八团」这个番号是不是太现代了？","url":"https://www.zhihu.com/question/338263871"},{"title":"如何评价任敏在电视剧《玉骨遥》中的演技？","url":"https://www.zhihu.com/question/609940716"},{"title":"67岁环卫工穿厚重制服在高温下工作，不穿罚款50元，城管局回应：长袖能够起防晒作用，对此你怎么看？","url":"https://www.zhihu.com/question/610461726"},{"title":"印度 6 月日经制造业 PMI 57.8 ，这一数据透露了哪些信息？","url":"https://www.zhihu.com/question/610064203"},{"title":"如何理解「微笑抑郁」，你身边有这样的人吗，当你感到抑郁时你会怎么排解？","url":"https://www.zhihu.com/question/610632846"},{"title":"如何看待2023中国汽车论坛上众车企签署的「汽车行业维护公平竞争市场秩序承诺书」？","url":"https://www.zhihu.com/question/610643415"},{"title":"76.1% 的农民工 60 岁后不愿休息，为何会出现这样的情况？他们的晚年如何「安放」？","url":"https://www.zhihu.com/question/610495725"},{"title":"2023 世界人工智能大会将展示 30 多款大模型，这对人工智能行业发展有哪些意义？","url":"https://www.zhihu.com/question/609545571"},{"title":"四大名著的作者里谁最能打?","url":"https://www.zhihu.com/question/594230092"},{"title":"显卡和CPU的硅脂多久换一次？","url":"https://www.zhihu.com/question/607981347"},{"title":"手机处理器好坏真的关乎到一部手机的成败吗？","url":"https://www.zhihu.com/question/609807228"},{"title":"开车忘记放下手刹，会对车辆安全有影响吗？","url":"https://www.zhihu.com/question/604182775"},{"title":"做「全职儿女」和做家庭主妇有什么不同？为什么「全职儿女」会被认为是「啃老」？","url":"https://www.zhihu.com/question/610276645"},{"title":"做「全职儿女」期间你学会了哪些新的生活技能？","url":"https://www.zhihu.com/question/610276756"},{"title":"作为「全职儿女」是一种怎样的体验？把爸妈当老板和出去工作有什么不同？","url":"https://www.zhihu.com/question/610276483"},{"title":"减肥怎么才能长久地坚持下去呢？","url":"https://www.zhihu.com/question/607743318"},{"title":"《三国杀》如果一个三血将拥有标风包全技能（无连营），能否打赢高达一号?","url":"https://www.zhihu.com/question/604374041"},{"title":"夏天去露营、海滩是否需要使用高倍防晒霜？","url":"https://www.zhihu.com/question/609226162"},{"title":"皮肤晒黑以后还可以白回来吗？","url":"https://www.zhihu.com/question/608118229"},{"title":"有哪些适合夏天的花果香或玫瑰调香水？","url":"https://www.zhihu.com/question/609258228"},{"title":"笔记本电脑核显、独显、集显有什么区别？","url":"https://www.zhihu.com/question/606089338"},{"title":"为什么小孩子不吃饭大人要追着满屋子跑？小孩子不会自己吃饭吗？","url":"https://www.zhihu.com/question/604573410"},{"title":"湖北一基层法庭宣传「调撤率 100%，无一判决」，法律学者认为「不宜过度提倡」，这反映出什么社会现象？","url":"https://www.zhihu.com/question/610470335"},{"title":"一直用手机拍照，要不要入一个相机？","url":"https://www.zhihu.com/question/607535929"},{"title":"去成都玩有什么推荐?","url":"https://www.zhihu.com/question/608268970"},{"title":"炎热天气到户外跑步，有哪些容易被大家忽视的注意事项？","url":"https://www.zhihu.com/question/609000295"},{"title":"新疆的火焰山，是否值得去打卡？","url":"https://www.zhihu.com/question/605319466"},{"title":"周末带宝宝出玩的婴儿车，该如何选择？","url":"https://www.zhihu.com/question/570852786"},{"title":"电影《消失的她》中，何非真的有精神病吗？","url":"https://www.zhihu.com/question/609561580"},{"title":"有没有性价比较高的吸尘器推荐？","url":"https://www.zhihu.com/question/397487619"},{"title":"新生儿护脐贴有什么用？","url":"https://www.zhihu.com/question/550057733"},{"title":"永雄停业风波后，记者卧底催收公司，发现各类灰色操作和软性威胁仍然存在，催收行业如何破解合规困境？","url":"https://www.zhihu.com/question/609749222"},{"title":"谷歌披露量子计算机新突破，经典超算需 47 年的任务可在几秒内完成，具有哪些意义？","url":"https://www.zhihu.com/question/610524870"},{"title":"Meta 正式推出新社媒平台 Threads，放话要取代推特，有哪些特点？未来是否可能取代推特？","url":"https://www.zhihu.com/question/610615844"},{"title":"「深夜拉群、积分打卡、朋友圈转发」打工人深受其害，中央整治形式主义专项会议召开，会带来改变吗？","url":"https://www.zhihu.com/question/610480659"},{"title":"由于对经济现状不满，英国苏格兰奥克尼群岛考虑「脱英入北欧」，哪些信息值得关注？","url":"https://www.zhihu.com/question/610225878"},{"title":"为什么nature没有nature mathematics这一子刊?","url":"https://www.zhihu.com/question/610118234"},{"title":"马斯克表示「未来地球上机器人数量将会多于人类数量」，如何看待这一观点？","url":"https://www.zhihu.com/question/610639241"},{"title":"马斯克称「全面自动驾驶将在今年年末到来，中国会有很强的人工智能能力」，哪些内容值得关注？","url":"https://www.zhihu.com/question/610631642"},{"title":"中国女足公布世界杯大名单，王霜吴海燕领衔，沈梦雨在列沈梦露落选，对中国女足的世界杯之旅有何期待？","url":"https://www.zhihu.com/question/610462511"},{"title":"调查称近 6 成受访者认为朋友圈无效社交多，如何看待此数据？你现在多久发一次朋友圈？","url":"https://www.zhihu.com/question/610625060"},{"title":"近期多地楼市政策陆续松绑，对提振近期楼市低迷有多大帮助？","url":"https://www.zhihu.com/question/609606548"},{"title":"未来手机是否会被 VR 眼镜取代？","url":"https://www.zhihu.com/question/605059370"}]