[{"title":"王毅称「中方出任本月安理会轮值主席，将与阿拉伯国家加强协调，主持公道」，透露了哪些信息？","url":"https://www.zhihu.com/question/628771107"},{"title":"年轻人是不是大部分时间都在「city work」，如何用一句话定义你的「city work」？","url":"https://www.zhihu.com/question/628795158"},{"title":"百胜中国一度大跌超 20%，创近 5 年最大跌幅，肯德基必胜客不香了？导致股价大跌的原因有哪些？","url":"https://www.zhihu.com/question/628778644"},{"title":"11 月 2 日创业板指高开低走跌近 1%，两市超 4000 只个股下跌，如何看待今日行情？","url":"https://www.zhihu.com/question/628775897"},{"title":"如何评价 10 月 31 日安踏宣布更改公司标志？","url":"https://www.zhihu.com/question/628636878"},{"title":"马斯克 X 公司估值已降至 190 亿美元，不到推特收购价一半，如何看待此事？","url":"https://www.zhihu.com/question/628659810"},{"title":"什么是「第一学历」，第一学历在应届生面试中占据怎样的地位？","url":"https://www.zhihu.com/question/628578755"},{"title":"著名开悟者萨古鲁说过：「人体需要的是休息，而不是睡眠不要试图提高自己的睡眠质量」如何理解？","url":"https://www.zhihu.com/question/621461019"},{"title":"TI12 决赛第三局比赛 Yatoro 被杀崩的 CK 是怎么刷到经济第一的？","url":"https://www.zhihu.com/question/628340527"},{"title":"23-24 赛季 NBA国王 101:102 勇士，如何评价这场比赛？","url":"https://www.zhihu.com/question/628773962"},{"title":"S13 八强赛 WBG vs NRG，你更看好谁？","url":"https://www.zhihu.com/question/628297977"},{"title":"也门胡塞武装发表声明证实，通过弹道导弹等，对以色列多个目标进行了大规模打击，这将对中东产生何种影响？","url":"https://www.zhihu.com/question/628653943"},{"title":"郑州女教师工作 3 个月跳楼轻生，遗书称「与教学无关工作太多」，教师的工作是怎样的？该如何为教师减负？","url":"https://www.zhihu.com/question/628672685"},{"title":"如何评价《DOTA2》职业选手 Yatoro？","url":"https://www.zhihu.com/question/628511189"},{"title":"23-24 赛季 NBA快船 125:130 湖人，如何评价这场比赛？","url":"https://www.zhihu.com/question/628773974"},{"title":"冬天开空调总是「头热脚冷」，空调制暖为何不能实现先暖足后暖身？","url":"https://www.zhihu.com/question/628663678"},{"title":"长沙爱之心养老公寓「爆雷」案六百余名受害老人起诉政府 7 部门，被驳回后上诉，如何从法律角度解读此事？","url":"https://www.zhihu.com/question/628384189"},{"title":"程序员是不是都要两个显示器？两个键盘？","url":"https://www.zhihu.com/question/627742159"},{"title":"化妆包里的哪些化妆小工具，可以帮上班族实现高效化妆？","url":"https://www.zhihu.com/question/628052667"},{"title":"文件存在彻底的删除吗？","url":"https://www.zhihu.com/question/619662369"},{"title":"《DOTA2》比赛为什么有时候观众觉得必 BanPick 的英雄，职业教练/选手却会做出迷之决策？","url":"https://www.zhihu.com/question/558841454"},{"title":"理想汽车 10 月交付量首次突破四万辆，同比增长 302.1%，盘前股价拉升，如何评价这一成绩？","url":"https://www.zhihu.com/question/628664764"},{"title":"想要打造一个家庭影院，有什么好方案推荐？","url":"https://www.zhihu.com/question/622906115"},{"title":"想入手一台Mac，大家觉得有哪些免费软件是必备的吗？","url":"https://www.zhihu.com/question/628644527"},{"title":"手机摄像拍照能力越来越强，单反相机还有市场吗？","url":"https://www.zhihu.com/question/628143544"},{"title":"美联储 11 月继续暂停加息，这意味着什么？背后有哪些原因？","url":"https://www.zhihu.com/question/628764854"},{"title":"明明交通很方便，为啥还要买车？","url":"https://www.zhihu.com/question/628634692"},{"title":"30＋的大龄实习律师如何找到神仙带教律师？年纪大了容不得试错，只想找到一个好师傅跟一辈子？","url":"https://www.zhihu.com/question/624152233"},{"title":"为何城市喜欢发展地下铁而不是地上铁(轻轨)?","url":"https://www.zhihu.com/question/628095222"},{"title":"梅西和迈阿密中国行取消，原定迈阿密 11 月将对阵中超球队，背后原因可能是什么？如何看待此事？","url":"https://www.zhihu.com/question/628690345"},{"title":"双11有哪些家电可以推荐？","url":"https://www.zhihu.com/question/492139850"},{"title":"怎样给moba英雄设计一个一击必杀的技能？","url":"https://www.zhihu.com/question/628369455"},{"title":"上大学后真的轻松了吗？","url":"https://www.zhihu.com/question/628661995"},{"title":"小时候的冬天，你们还记得吗？","url":"https://www.zhihu.com/question/628328713"},{"title":"如今的商场，好像存在两个世界：楼上人烟稀少， B1、B2 却人声鼎沸，为何出现这种现象？","url":"https://www.zhihu.com/question/628796562"},{"title":"双11有哪些高性价的入门级耳机可以选择？","url":"https://www.zhihu.com/question/627773550"},{"title":"到付尾款的时候了，大家都入手了哪些好物？","url":"https://www.zhihu.com/question/628593654"},{"title":"你曾经为了睡个好觉都做了哪些事情？","url":"https://www.zhihu.com/question/626638215"},{"title":"工作中遇到领导不合理的安排怎么办？","url":"https://www.zhihu.com/question/628269672"},{"title":"康师傅饮品宣布涨价 0.5-1 元，全国零售价将统一调整，线下具体执行还需时间，有何影响？","url":"https://www.zhihu.com/question/628808626"},{"title":"日本开始第三轮核污染水排海，下一轮预计明年初开始，四轮总量约 3.12 万吨，哪些信息值得关注？","url":"https://www.zhihu.com/question/628786990"},{"title":"上班族如何在中午有氧锻炼？","url":"https://www.zhihu.com/question/626834505"},{"title":"2023年梅西获得第八座金球奖，你是怎样的心情?","url":"https://www.zhihu.com/question/628468160"},{"title":"美的自研的180° 环游风道技术，在导风效果及舒适体验上表现如何？","url":"https://www.zhihu.com/question/628519835"},{"title":"如何评价《咒术回战》第241话？","url":"https://www.zhihu.com/question/628657735"},{"title":"天猫双十一新增人工智能服务类目，这对商家来说机会在哪里？","url":"https://www.zhihu.com/question/628666937"},{"title":"在网购时总会因为担心快递是否损坏产生焦虑，对此你有哪些「解决焦虑」的方法？","url":"https://www.zhihu.com/question/628643585"},{"title":"Canyon 采访疑似透露将与 ShowMaker 解绑，如何评价这几年来这对 DK 中野的表现？","url":"https://www.zhihu.com/question/628511679"},{"title":"核心骨干员工离职，如何做好离职面谈？","url":"https://www.zhihu.com/question/626857405"},{"title":"你买衣服的时候一般都买什么牌子呢？","url":"https://www.zhihu.com/question/378557691"}]