[{"title":"汽车会顶替房地产，成为经济的扛把子产业吗？","url":"https://www.zhihu.com/question/639211301"},{"title":"屏下指纹这么成熟的技术，iPhone 为什么不用？","url":"https://www.zhihu.com/question/463547475"},{"title":"美军 3 艘航母奔赴中国周边，解放军南部战区将于南海巡航，哪些信息值得关注？","url":"https://www.zhihu.com/question/640792598"},{"title":"马云、蔡崇信大幅增持阿里巴巴，如何看待这一举动？有哪些值得关注的信息？","url":"https://www.zhihu.com/question/640866137"},{"title":"财政部表示将研究制定国家「保基本民生、保工资、保运转」清单，对具备条件事项制定基本保障标准，如何解读？","url":"https://www.zhihu.com/question/640790998"},{"title":"如何评价《崩坏：星穹铁道》黄泉角色立绘？","url":"https://www.zhihu.com/question/640821636"},{"title":"如何评价《崩坏 星穹铁道》新PV曝光新角色“黄泉”？","url":"https://www.zhihu.com/question/640815647"},{"title":"金钏儿的死在薛宝钗眼中算什么？","url":"https://www.zhihu.com/question/639709199"},{"title":"猫咪有时间概念吗？为什么每天回家她都能准时在门口接我？","url":"https://www.zhihu.com/question/639819263"},{"title":"1 月 23 日新疆阿克苏地区乌什县发生 7.1级地震，应急管理部启动地震三级应急响应，目前情况如何？","url":"https://www.zhihu.com/question/640763089"},{"title":"当老师久了，真的能一眼就看出一个学生聪不聪明吗？","url":"https://www.zhihu.com/question/639222741"},{"title":"任天堂宝可梦公司前法务负责人表示幻兽帕鲁像「胡乱抄袭」，如何看待此事？","url":"https://www.zhihu.com/question/640813583"},{"title":"有人说，两块钱的维生素C大多都是右旋，这是真的吗？","url":"https://www.zhihu.com/question/632333865"},{"title":"加特林机枪为什么不需要专门的散热系统？","url":"https://www.zhihu.com/question/270349184"},{"title":"茅台与瑞幸再出新品，开卖首日未现排队场面，专家称「没有持续火爆很正常」，如何看待此事？","url":"https://www.zhihu.com/question/640782312"},{"title":"80% 的学校还在给新生上 C 语言，是它们 OUT 了吗？","url":"https://www.zhihu.com/question/640594091"},{"title":"吃哈尔滨红肠蘸醋对北方人意味着什么?","url":"https://www.zhihu.com/question/640564210"},{"title":"极右翼政党「驱逐移民」计划引全德愤怒，超百万人走上街头称「决不能重蹈纳粹覆辙」，如何解读？","url":"https://www.zhihu.com/question/640657748"},{"title":"经济学家称，「 A 股今年有望走出前低后高走势，投资者要保持理性，多看少动」，如何看待这一言论？","url":"https://www.zhihu.com/question/640804144"},{"title":"为什么年轻人喜欢把旧手机给父母呢?","url":"https://www.zhihu.com/question/640014851"},{"title":"领导跟我说公司裁员将二选一，偏向于留下我，但被裁同事的工作都会让我接手，我该怎么回复呢？","url":"https://www.zhihu.com/question/640546143"},{"title":"以外长声称要给加沙造由以色列控制的人工岛，引欧盟外长不满，该计划表露出什么意图？如何评价？","url":"https://www.zhihu.com/question/640808196"},{"title":"卡塔尔亚洲杯，国足小组赛遭淘汰，如何评价他们的表现？","url":"https://www.zhihu.com/question/640851428"},{"title":"碧桂园拟转让广州多处资产，合计拟转让价格 38.18 亿元，哪些信息值得关注？","url":"https://www.zhihu.com/question/640782399"},{"title":"《原神》里有哪些角色是你看立绘第一眼就喜欢上的，哪些角色是你做了剧情才喜欢上的？","url":"https://www.zhihu.com/question/638822444"},{"title":"美英再次空袭也门胡塞武装目标，具体情况如何？将对红海局势带来哪些影响？","url":"https://www.zhihu.com/question/640784074"},{"title":"2024 年春节，有什么好吃的零食推荐么？","url":"https://www.zhihu.com/question/638297513"},{"title":"2024年的第一本书，你计划读什么？","url":"https://www.zhihu.com/question/637328514"},{"title":"有哪些你小时候过年的年味，现在的小朋友很难体验到了？","url":"https://www.zhihu.com/question/637948573"},{"title":"你觉得 2023年最接近完美的笔记本电脑是哪一台？","url":"https://www.zhihu.com/question/639903696"},{"title":"极度自律的人，内心会痛苦吗？","url":"https://www.zhihu.com/question/640085675"},{"title":"C 罗因伤无法出场，利雅得胜利中国行比赛延期，哪些信息值得关注？","url":"https://www.zhihu.com/question/640824157"},{"title":"某一天你发现你的孩子很有运动天赋，你会让他去学网球，篮球，羽毛球，乒乓球还是足球?","url":"https://www.zhihu.com/question/580508500"},{"title":"老一辈常说「吃得苦中苦，方为人上人」如何反驳这一观点？","url":"https://www.zhihu.com/question/640085691"},{"title":"为什么小时候不能支配钱和时间，还是有很多人想回去?","url":"https://www.zhihu.com/question/640085678"},{"title":"以色列提议停火 60 天换所有 130 名人质，如何看待这一举动？以巴能否达成长期停火？","url":"https://www.zhihu.com/question/640802755"},{"title":"ETF 融券火爆，有券商透露「500ETF、1000ETF 已无券可借」，哪些信息值得关注？","url":"https://www.zhihu.com/question/640840756"},{"title":"如何看待陈仙辉院士主讲央视财经频道《中国经济大讲堂——神奇的超导体》，并表示室温超导并非无法实现？","url":"https://www.zhihu.com/question/640704355"},{"title":"23-24赛季NBA马刺123:133负76 人，恩比德狂轰70+18，文班33，如何评价这场比赛？","url":"https://www.zhihu.com/question/640781178"},{"title":"哈马斯拒绝以色列停火两个月提议，以军遭遇「损失最惨重一天」，24 名士兵死亡，目前巴以冲突局势如何？","url":"https://www.zhihu.com/question/640924565"},{"title":"新疆乌什 7.1 级地震后平均每 12 分钟发生一次 3 级余震，将会带来哪些影响？","url":"https://www.zhihu.com/question/640842136"},{"title":"美民众收到 AI 拜登来电称「不要出门给特朗普投票」，是否涉及干预选举？本次大选还出现了哪些拉票手段？","url":"https://www.zhihu.com/question/640815658"},{"title":"为什么我的原生家庭很幸福，但我却患了抑郁症？","url":"https://www.zhihu.com/question/636448638"},{"title":"开屏弹窗「乱跳转」，闲鱼、高德地图等应用被工信部通报，app弹窗跳转问题是否有望彻底解决？","url":"https://www.zhihu.com/question/640814903"},{"title":"员工下班后回复工作消息「隐形加班」，公司被判赔 3 万元加班费创全国首例，如何从法律角度看待此事？","url":"https://www.zhihu.com/question/640804999"},{"title":"云南镇雄山体滑坡灾害已致 31 人遇难，当前救援存在哪些难点？","url":"https://www.zhihu.com/question/640781088"},{"title":"运动中的哪个瞬间让你深刻感受到，「你必须很努力，才能看上去毫不费力」？","url":"https://www.zhihu.com/question/640651630"},{"title":"同一只猫咪在不同照片里，颜值差异可以有多大？","url":"https://www.zhihu.com/question/639819312"},{"title":"家用NAS，有什么好的推荐？","url":"https://www.zhihu.com/question/630932905"},{"title":"有没有一种蔬菜，你吃到后就感觉「要过年了」？","url":"https://www.zhihu.com/question/639053176"}]