[{"title":"字节跳动大模型训练被实习生恶意注入病毒，涉事者已被辞退，攻击带来的影响有多大？暴露出哪些问题？","url":"https://www.zhihu.com/question/1296528119"},{"title":"临沂一中介称「今年已卖出 20 多个孩子」，官方回应「该中介已传唤到案」，涉案人员将承担哪些法律责任？","url":"https://www.zhihu.com/question/1259014200"},{"title":"脱口秀演员调侃歌手 GAI 嘴歪，GAI 发文怒怼，曾称歪嘴是因为生病，脱口秀表演如何注意表达边界？","url":"https://www.zhihu.com/question/1284883865"},{"title":"S14淘汰赛HLE1:3不敌BLG止步八强，这场比赛他们输在哪里？BLG又赢在哪里？","url":"https://www.zhihu.com/question/1309817522"},{"title":"为什么西游记几乎不提北俱芦洲?","url":"https://www.zhihu.com/question/962924281"},{"title":"「疫情班」应届生遭就业歧视，企业认为其「分层严重，分辨成本高」、「疫情期没学到技能」，反映出哪些问题？","url":"https://www.zhihu.com/question/1258506906"},{"title":"如何评价综艺《喜剧之王单口季》总决赛？","url":"https://www.zhihu.com/question/1297015366"},{"title":"当过大学生以后，你们还会留恋高中生活吗？","url":"https://www.zhihu.com/question/1204801442"},{"title":"S14 淘汰赛 BLG 3:1 淘汰 HLE 晋级四强，如何评价这场比赛？","url":"https://www.zhihu.com/question/1289984189"},{"title":"10 月 18 日 A 股大涨，两市成交额超 2 万亿，科创50指数大涨超 11%，这轮调整到头了吗？","url":"https://www.zhihu.com/question/1235750246"},{"title":"现在为智驾买单，是不是“智商税”？","url":"https://www.zhihu.com/question/737789031"},{"title":"狗狗知道主人睡觉，会故意轻手轻脚活动吗?","url":"https://www.zhihu.com/question/350491086"},{"title":"火箭发射时喷出的火焰高达三千多度，为何它没有把自己融化掉？","url":"https://www.zhihu.com/question/638955635"},{"title":"现实中有没有类似「北乔峰南慕容」这样表面齐名，但实际上才器相差甚远的例子？","url":"https://www.zhihu.com/question/27738577"},{"title":"读鲁迅的《藤野先生》，有点疑惑，为什么藤野先生会对一个异国的学生特殊对待和关照？","url":"https://www.zhihu.com/question/625668015"},{"title":"本人在学九年级历史，有一个问题，为什么在法国大革命之前法国都是国王，为什么到拿破仑这里直接就是皇帝?","url":"https://www.zhihu.com/question/1086097199"},{"title":"央行行长潘功胜称，择机下调存款准备金率和 LPR 0.25-0.5 个百分点 ，释放了什么信号？","url":"https://www.zhihu.com/question/1243038453"},{"title":"有人提前发现了是红孩儿假扮的萍萍吗？","url":"https://www.zhihu.com/question/667343874"},{"title":"5000 亿互换便利操作细则出炉，质押率不超 90%，证监会同意20家机构开展操作，对市场有何影响？","url":"https://www.zhihu.com/question/1268646198"},{"title":"10 月 18 日全锦赛男团半决赛，樊振东 3-2 险胜程靖淇，你认为本场比赛双方发挥如何？","url":"https://www.zhihu.com/question/1285583131"},{"title":"平时很爱我的猫猫，为什么在我假装晕倒后「不理不睬」的绕过去了？","url":"https://www.zhihu.com/question/667976595"},{"title":"近期一款由AI辅助制作的魔性游戏「沙威玛传奇」爆火，如何看待独立游戏中用AI辅助作画的作品逐渐变多？","url":"https://www.zhihu.com/question/871157123"},{"title":"《一人之下》中倒转八方(人磁)的能力上限最高能达到什么境界?","url":"https://www.zhihu.com/question/623921570"},{"title":"为什么和猫说话会感觉到快乐？","url":"https://www.zhihu.com/question/615903139"},{"title":"springboot每个web请求是一个线程吗？","url":"https://www.zhihu.com/question/314356750"},{"title":"本人很爱看书想辞职，全职写小说可以吗？","url":"https://www.zhihu.com/question/666596698"},{"title":"为什么很多 19 世纪的欧洲文学作品多次提到拿破仑，并且对拿破仑赞誉有加呢?","url":"https://www.zhihu.com/question/793868163"},{"title":"如何评价日本漫画《石纪元》？","url":"https://www.zhihu.com/question/305544429"},{"title":"养宠物到底有多治愈？","url":"https://www.zhihu.com/question/657319736"},{"title":"S14世界赛哪只战队最可能夺冠？","url":"https://www.zhihu.com/question/700344207"}]